{
  "facebook": "",
  "GOTS": "X",
  "RSW (Responsible Wool Standard)": "",
  "productTypes": [
    "bolsos-y-mochilas"
  ],
  "OKTEX": "",
  "Empresa B": "",
  "name": "The Ecobag Company",
  "Fair Trade Certified": "",
  "OCS100": "",
  "genders": [
    "women",
    "unisex"
  ],
  "instagram": "https://www.instagram.com/theecobagcompany/",
  "pictures": [
    "https://res.cloudinary.com/dq9k7gnud/image/upload/v1588863401/PERU/THE%20ECOBAG%20COMPANY/67885529_193352035013437_9110151791515070641_n_pko5us.jpg",
    "https://res.cloudinary.com/dq9k7gnud/image/upload/v1588863400/PERU/THE%20ECOBAG%20COMPANY/74607031_2444209525838491_8329837563894152498_n_gkng1k.jpg"
  ],
  "country": "peru",
  "website": "https://ewaya.pe/marca/the-ecobag-company/",
  "description": "Bolsos & complementos para una vida plastic-free. Algodón orgánico & fibras sostenibles. Hecho a mano en Perú.",
  "criteria": [
    "materiales-organicos",
    "fibras-naturales",
    "produccion-local",
    "empoderamiento-de-la-mujer"
  ]
}