{"GOTS":"","Empresa B":"","OKTEX":"","OCS100":"","Fair Trade Certified":"","RSW (Responsible Wool Standard)":"","country":"peru","name":"Ayni","website":"http://ayni.com.pe","instagram":"https://www.instagram.com/ayniuniverse/","facebook":"","description":"AYNI se creó a partir de un amor común por los productos de alta calidad, los mejores materiales de la naturaleza y un fuerte compromiso social, económico y medioambiental. Todos nuestros productos están diseñados y fabricados en Perú, un país con una de las economías de más rápido crecimiento del mundo, que utiliza solo los materiales peruanos más exclusivos, como la lujosa alpaca bebé y el algodón Pima.","criteria":["materiales-organicos","fibras-naturales","produccion-local"],"genders":["Women"],"productTypes":["vestimenta","eco-lujo"]}
