{"GOTS":"","Empresa B":"","OKTEX":"","OCS100":"","Fair Trade Certified":"","RSW (Responsible Wool Standard)":"","country":"uruguay","name":"Chiaramo","website":"https://www.facebook.com/chiaramo.uy","instagram":"https://www.instagram.com/chiaramo.uy/","facebook":"","description":"Empezamos en 2015 creando accesorios, con el paso del tiempo transicionamos hacia un camino más verde. Hasta hoy seguimos en eso, renovando, aprendiendo y sobre todo, con el mismo entusiasmo. Vivi, sentí y disfruta de la naturaleza cuidándola.","criteria":["materiales-reciclados","produccion-local"],"genders":["Women"],"productTypes":["joyeria"]}
