{"GOTS":"","Empresa B":"","OKTEX":"","OCS100":"","Fair Trade Certified":"","RSW (Responsible Wool Standard)":"","country":"mexico","name":"Coeur","website":"https://www.coeur.mx","instagram":"https://www.instagram.com/coeur.mx/?hl=es","facebook":"","description":"Cœur es una colección de prendas que logra combinar la simplicidad con los detalles. Deseando ir en contra de las tendencias en constante cambio y el consumo acelerado, el diseño de Coeur gira entorno a prendas para el uso diario enfatizando la importancia de la versatilidad y el diseño meticuloso. Desde la conceptualización de una nueva prenda hasta el producto final, todas las piezas de Coeur están diseñadas, desarrolladas y fabricadas en México por un pequeño y talentoso equipo de trabajo.","criteria":["a-pedido","materiales-organicos","produccion-local","integracion-social"],"genders":["women"],"productTypes":["vestimenta"]}
